{"course_code": "MA4001", "course_name": "ENGINEERING DESIGN", "academic_units": 4.0, "indexes": [{"index": "23423", "lessons": [{"lesson_type": "LEC/STUDIO", "group": "LE", "day": "MON", "time": "1130-1220", "venue": "LT1A", "remark": ""}, {"lesson_type": "TUT", "group": "MA1", "day": "MON", "time": "1330-1620", "venue": "LHN-TR+08", "remark": "Teaching Wk2-13"}]}, {"index": "23424", "lessons": [{"lesson_type": "LEC/STUDIO", "group": "LE", "day": "MON", "time": "1130-1220", "venue": "LT1A", "remark": ""}, {"lesson_type": "TUT", "group": "MA2", "day": "MON", "time": "1330-1620", "venue": "LHN-TR+07", "remark": "Teaching Wk2-13"}]}, {"index": "23425", "lessons": [{"lesson_type": "LEC/STUDIO", "group": "LE", "day": "MON", "time": "1130-1220", "venue": "LT1A", "remark": ""}, {"lesson_type": "TUT", "group": "MA3", "day": "TUE", "time": "1330-1620", "venue": "LHN-TR+08", "remark": "Teaching Wk2-13"}]}, {"index": "23426", "lessons": [{"lesson_type": "LEC/STUDIO", "group": "LE", "day": "MON", "time": "1130-1220", "venue": "LT1A", "remark": ""}, {"lesson_type": "TUT", "group": "MA4", "day": "TUE", "time": "1330-1620", "venue": "LHN-TR+07", "remark": "Teaching Wk2-13"}]}, {"index": "23427", "lessons": [{"lesson_type": "LEC/STUDIO", "group": "LE", "day": "MON", "time": "1130-1220", "venue": "LT1A", "remark": ""}, {"lesson_type": "TUT", "group": "MA5", "day": "WED", "time": "1330-1620", "venue": "LHN-TR+08", "remark": "Teaching Wk2-13"}]}, {"index": "23428", "lessons": [{"lesson_type": "LEC/STUDIO", "group": "LE", "day": "MON", "time": "1130-1220", "venue": "LT1A", "remark": ""}, {"lesson_type": "TUT", "group": "MA6", "day": "WED", "time": "1330-1620", "venue": "LHN-TR+07", "remark": "Teaching Wk2-13"}]}, {"index": "23429", "lessons": [{"lesson_type": "LEC/STUDIO", "group": "LE", "day": "MON", "time": "1130-1220", "venue": "LT1A", "remark": ""}, {"lesson_type": "TUT", "group": "MA7", "day": "THU", "time": "1330-1620", "venue": "LHN-TR+07", "remark": "Teaching Wk2-13"}]}]}