{"course_code": "MS4631", "course_name": "CORROSION ENGINEERING*~", "academic_units": 3.0, "indexes": [{"index": "15381", "lessons": [{"lesson_type": "LEC/STUDIO", "group": "LE", "day": "FRI", "time": "1530-1720", "venue": "LHN-LT", "remark": ""}, {"lesson_type": "TUT", "group": "T1", "day": "THU", "time": "1030-1120", "venue": "TR+17", "remark": "Teaching Wk2-13"}]}, {"index": "15382", "lessons": [{"lesson_type": "LEC/STUDIO", "group": "LE", "day": "FRI", "time": "1530-1720", "venue": "LHN-LT", "remark": ""}, {"lesson_type": "TUT", "group": "T1", "day": "THU", "time": "1030-1120", "venue": "TR+17", "remark": "Teaching Wk2-13"}]}]}