{"course_code": "SS5104", "course_name": "BASKETBALL*~", "academic_units": 3.0, "indexes": [{"index": "68111", "lessons": [{"lesson_type": "TUT", "group": "1", "day": "MON", "time": "1530-1820", "venue": "NIE5-B2-04", "remark": ""}]}, {"index": "68112", "lessons": [{"lesson_type": "TUT", "group": "2", "day": "TUE", "time": "0830-1120", "venue": "NIE5-B2-04", "remark": ""}]}, {"index": "68113", "lessons": [{"lesson_type": "TUT", "group": "3", "day": "WED", "time": "1830-2120", "venue": "NIE5-B2-04", "remark": ""}]}]}